MANIFEST.in
README.rst
setup.py
django_graphql_playground.egg-info/PKG-INFO
django_graphql_playground.egg-info/SOURCES.txt
django_graphql_playground.egg-info/dependency_links.txt
django_graphql_playground.egg-info/top_level.txt
graphql_playground/__init__.py
graphql_playground/apps.py
graphql_playground/tests.py
graphql_playground/views.py
graphql_playground/__pycache__/__init__.cpython-37.pyc
graphql_playground/__pycache__/views.cpython-37.pyc
graphql_playground/templates/playground/playground.html