Metadata-Version: 2.1
Name: django-graphql-playground
Version: 1.0
Summary: Apollo GraphQL Playground as a Django view
Home-page: https://jaydenwindle.com/
Author: Jayden Windle
Author-email: jaydenwindle@gmail.com
License: MIT License
Platform: UNKNOWN
